README.rst
setup.py
item/__init__.py
item/const.py
item/decorator.py
item/error.py
item/field.py
item/item.py
item.egg-info/PKG-INFO
item.egg-info/SOURCES.txt
item.egg-info/dependency_links.txt
item.egg-info/requires.txt
item.egg-info/top_level.txt
script/__init__.py
script/test.py
test/__init__.py
test/item.py